hierarchical_prophet/__init__.py
hierarchical_prophet/_utils.py
hierarchical_prophet/base.py
hierarchical_prophet/exogenous_priors.py
hierarchical_prophet/hierarchical_prophet/__init__.py
hierarchical_prophet/hierarchical_prophet/_changepoint_matrix.py
hierarchical_prophet/hierarchical_prophet/_distribution.py
hierarchical_prophet/hierarchical_prophet/_expand_column_per_level.py
hierarchical_prophet/hierarchical_prophet/_time_scaler.py
hierarchical_prophet/hierarchical_prophet/prophet.py
hierarchical_prophet/jax_functions.py
hierarchical_prophet/logger.py
hierarchical_prophet/logistic.py
hierarchical_prophet/multiindex.py
hierarchical_prophet/prophet/__init__.py
hierarchical_prophet/prophet/prophet.py
hierarchical_prophet-0.0.1.dist-info/LICENSE
hierarchical_prophet-0.0.1.dist-info/METADATA
hierarchical_prophet-0.0.1.dist-info/WHEEL
hierarchical_prophet-0.0.1.dist-info/RECORD
