Metadata-Version: 2.1
Name: hierarchical-prophet
Version: 0.0.1
Summary: 
Author: Felipe Angelim
Author-email: felipeangelim@gmail.com
Requires-Python: >=3.9,<3.13
Classifier: Programming Language :: Python :: 3
Classifier: Programming Language :: Python :: 3.9
Classifier: Programming Language :: Python :: 3.10
Classifier: Programming Language :: Python :: 3.11
Requires-Dist: mkdocs-material (>=9.5.14,<10.0.0)
Requires-Dist: numpyro (>=0.13.2,<0.14.0)
Requires-Dist: sktime (>=0.21)
